bisslog_schema/__init__.py
bisslog_schema/cli.py
bisslog_schema/eager_import_module_or_package.py
bisslog_schema/service_full_metadata_reader.py
bisslog_schema/service_metadata_with_code.py
bisslog_schema/commands/__init__.py
bisslog_schema/commands/analyze_metadata_file/__init__.py
bisslog_schema/commands/analyze_metadata_file/analyze_metadata.py
bisslog_schema/commands/analyze_metadata_file/metadata_analysis_report.py
bisslog_schema/schema/__init__.py
bisslog_schema/schema/base_obj_schema.py
bisslog_schema/schema/entity_info.py
bisslog_schema/schema/external_interaction.py
bisslog_schema/schema/read_metadata.py
bisslog_schema/schema/service_info.py
bisslog_schema/schema/use_case_info.py
bisslog_schema/schema/enums/__init__.py
bisslog_schema/schema/enums/criticality.py
bisslog_schema/schema/enums/event_delivery_semantic.py
bisslog_schema/schema/enums/trigger_type.py
bisslog_schema/schema/enums/type_external_interaction.py
bisslog_schema/schema/triggers/__init__.py
bisslog_schema/schema/triggers/trigger_consumer.py
bisslog_schema/schema/triggers/trigger_http.py
bisslog_schema/schema/triggers/trigger_info.py
bisslog_schema/schema/triggers/trigger_mappable.py
bisslog_schema/schema/triggers/trigger_options.py
bisslog_schema/schema/triggers/trigger_schedule.py
bisslog_schema/schema/triggers/trigger_websocket.py
bisslog_schema/setup/__init__.py
bisslog_schema/setup/bisslog_setup_deco.py
bisslog_schema/setup/bisslog_setup_registry.py
bisslog_schema/setup/runtime_type.py
bisslog_schema/setup/setup_metadata.py
bisslog_schema/use_case_code_inspector/__init__.py
bisslog_schema/use_case_code_inspector/package_tree_reader.py
bisslog_schema/use_case_code_inspector/use_case_analyzer_base.py
bisslog_schema/use_case_code_inspector/use_case_code_metadata.py
bisslog_schema/use_case_code_inspector/strategies/__init__.py
bisslog_schema/use_case_code_inspector/strategies/use_case_metadata_module_inspector.py
bisslog_schema/use_case_code_inspector/strategies/use_case_module_inspector.py
bisslog_schema-0.0.10.dist-info/licenses/LICENSE
bisslog_schema-0.0.10.dist-info/METADATA
bisslog_schema-0.0.10.dist-info/WHEEL
bisslog_schema-0.0.10.dist-info/entry_points.txt
bisslog_schema-0.0.10.dist-info/top_level.txt
bisslog_schema-0.0.10.dist-info/RECORD
