Metadata-Version: 2.4
Name: bisslog_schema
Version: 0.0.10
Summary: It is a lightweight framework to organize and document the key elements of a distributed system, focusing on its use cases and service design. It structures the metadata without exposing any underlying technical or implementation-specific details.
Author-email: Darwin Stiven Herrera Cartagena <darwinsherrerac@gmail.com>
Project-URL: Homepage, https://github.com/darwinhc/bisslog-schema-py
Keywords: hexagonal,adapters,bisslog
Classifier: Programming Language :: Python :: 3
Classifier: Operating System :: OS Independent
Requires-Python: >=3.7
License-File: LICENSE
Provides-Extra: yaml
Requires-Dist: PyYAML>=6.0; extra == "yaml"
Provides-Extra: timezone
Requires-Dist: backports.zoneinfo>=0.2.1; python_version < "3.9" and extra == "timezone"
Dynamic: license-file
